mcp_mem/__about__.py
mcp_mem/__init__.py
mcp_mem/__main__.py
mcp_mem/config.py
mcp_mem/memory_utils.py
mcp_mem/server.py
mcp_mem-0.1.0.dist-info/licenses/LICENSE
mcp_mem-0.1.0.dist-info/METADATA
mcp_mem-0.1.0.dist-info/WHEEL
mcp_mem-0.1.0.dist-info/entry_points.txt
mcp_mem-0.1.0.dist-info/top_level.txt
mcp_mem-0.1.0.dist-info/RECORD
