Metadata-Version: 2.4
Name: mcp-mem
Version: 0.1.0
Summary: An MCP server implementing memory solution for data-rich applications
Home-page: https://github.com/ddkang1/mcp-mem
Author: Don Kang
Author-email: Don Kang <donkang34@gmail.com>
License: MIT License
Project-URL: Homepage, https://github.com/ddkang1/mcp-mem
Project-URL: Bug Tracker, https://github.com/ddkang1/mcp-mem/issues
Project-URL: Documentation, https://github.com/ddkang1/mcp-mem#readme
Classifier: Development Status :: 3 - Alpha
Classifier: Intended Audience :: Developers
Classifier: License :: OSI Approved :: MIT License
Classifier: Programming Language :: Python :: 3
Classifier: Programming Language :: Python :: 3.10
Requires-Python: >=3.10
License-File: LICENSE
Requires-Dist: mcp>=1.2.0
Requires-Dist: uvicorn>=0.15.0
Requires-Dist: starlette>=0.17.1
Requires-Dist: hipporag>=0.1.0
Provides-Extra: dev
Requires-Dist: pytest>=7.0.0; extra == "dev"
Requires-Dist: pytest-asyncio>=0.18.0; extra == "dev"
Requires-Dist: black>=22.1.0; extra == "dev"
Requires-Dist: isort>=5.10.1; extra == "dev"
Requires-Dist: mypy>=0.931; extra == "dev"
Requires-Dist: flake8>=4.0.1; extra == "dev"
Dynamic: author
Dynamic: home-page
Dynamic: license-file
Dynamic: requires-python
